joeflow/__init__.py
joeflow/_version.py
joeflow/admin.py
joeflow/apps.py
joeflow/conf.py
joeflow/forms.py
joeflow/models.py
joeflow/typing.py
joeflow/utils.py
joeflow/views.py
joeflow/contrib/__init__.py
joeflow/contrib/reversion.py
joeflow/management/__init__.py
joeflow/management/commands/__init__.py
joeflow/management/commands/render_workflow_graph.py
joeflow/migrations/0001_initial.py
joeflow/migrations/__init__.py
joeflow/runner/__init__.py
joeflow/runner/celery.py
joeflow/runner/dramatiq.py
joeflow/tasks/__init__.py
joeflow/tasks/human.py
joeflow/tasks/machine.py
joeflow-2.0.2.dist-info/licenses/LICENSE
joeflow-2.0.2.dist-info/WHEEL
joeflow-2.0.2.dist-info/METADATA
joeflow-2.0.2.dist-info/RECORD
